debouncer.vhd
library IEEE;
use IEEE.std_logic_1164.all;
use IEEE.numeric_std.all;

-- Debouncer circuit:
-- se bottone cambia, si resetta counter
-- se bottone non cambia, counter=counter-1
-- se counter = 0 ==> valore bottone stabile
-- si attiva l'uscita per un periodo di clock solo se valore stabile =/= segnale bottone nel ciclo precedente

entity Debouncer is
    port(button_in : in std_logic;
         clock : in std_logic;
         reset : in std_logic;
         pulse_out : out std_logic
        );
end Debouncer;

architecture Behavioural of Debouncer is
    constant MAX_COUNTS : integer := 15; -- lui tira un impulso ogni 15 cicli di clock, se la pressione dura più di 15 cicli
    constant BTN_ACTIVE_LOGIC : std_logic := '1';

    signal counter : integer := 0;
    signal state : std_logic := '0'; -- 0: idle, 1: wait_time
begin
    process(reset, clock)
    begin
        if (reset = '1') then
            pulse_out <= '0';
            state <= '0';
        elsif (rising_edge(clock)) then
            case(state) is
                when '0' =>
                    if(button_in = BTN_ACTIVE_LOGIC) then
                        state <= '1';
                    else
                        state <= '0';
                    end if;
                    pulse_out <= '0';
                when '1' =>
                    if (counter = MAX_COUNTS) then
                        counter <= 0;
                        if (button_in = BTN_ACTIVE_LOGIC) then
                            pulse_out <= '1';
                        end if;
                        state <= '0';
                    else
                        counter <= counter + 1;
                    end if;
                when others =>
                    
            end case;
        end if;
    end process;
end architecture Behavioural;

testbench.vhd
library IEEE;
use IEEE.std_logic_1164.all;
use IEEE.numeric_std.all;

ENTITY tb_alu IS
END tb_alu;
 
ARCHITECTURE behavior OF tb_alu IS 
 
    -- Component Declaration for the Unit Under Test (UUT)
 
    component Debouncer
    port(
         clock : in  std_logic;
         reset : in  std_logic;
         button_in : in  std_logic;
         pulse_out : out  std_logic
        );
    end component;
    

   --Inputs
   signal clock : std_logic := '0';
   signal reset : std_logic := '0';
   signal button_in : std_logic := '0';

    --Outputs
   signal pulse_out : std_logic;

   -- clock period definitions
   constant clock_period : time := 10 ns;
 
BEGIN
 
    -- Instantiate the Unit Under Test (UUT)
   uut: Debouncer PORT MAP (
          clock => clock,
          reset => reset,
          button_in => button_in,
          pulse_out => pulse_out
        );

   -- clock process definitions
   clock_process :process
   begin
        clock <= '0';
        wait for clock_period/2;
        clock <= '1';
        wait for clock_period/2;
   end process;
 

   -- Stimulus process
   stim_proc: process
   begin        
        button_in <= '0';
        reset <= '1';
      -- hold reset state for 100 ns.
      wait for 100 ns;
        reset <= '0';
      wait for clock_period*10;
        --first activity
        button_in <= '1';   wait for clock_period*2;
        button_in <= '0';   wait for clock_period*1;
        button_in <= '1';   wait for clock_period*1;
        button_in <= '0';   wait for clock_period*20;
        --second activity
        button_in <= '1';   wait for clock_period*1;
        button_in <= '0';   wait for clock_period*1;
        button_in <= '1';   wait for clock_period*1;
        button_in <= '0';   wait for clock_period*2;
        button_in <= '1';   wait for clock_period*20;
        button_in <= '0';   
      wait;
   end process;

END;

testbench.vcd
$date
  Thu Nov 25 12:01:39 2021
$end
$version
  GHDL v0
$end
$timescale
  1 fs
$end
$scope module standard $end
$upscope $end
$scope module std_logic_1164 $end
$upscope $end
$scope module numeric_std $end
$upscope $end
$scope module tb_alu $end
$var reg 1 ! clock $end
$var reg 1 " reset $end
$var reg 1 # button_in $end
$var reg 1 $ pulse_out $end
$scope module uut $end
$var reg 1 % button_in $end
$var reg 1 & clock $end
$var reg 1 ' reset $end
$var reg 1 ( pulse_out $end
$var integer 32 ) counter $end
$var reg 1 * state $end
$upscope $end
$upscope $end
$enddefinitions $end
#0
0!
1"
0#
0$
0%
0&
1'
0(
b0 )
0*
#5000000
1!
1&
#10000000
0!
0&
#15000000
1!
1&
#20000000
0!
0&
#25000000
1!
1&
#30000000
0!
0&
#35000000
1!
1&
#40000000
0!
0&
#45000000
1!
1&
#50000000
0!
0&
#55000000
1!
1&
#60000000
0!
0&
#65000000
1!
1&
#70000000
0!
0&
#75000000
1!
1&
#80000000
0!
0&
#85000000
1!
1&
#90000000
0!
0&
#95000000
1!
1&
#100000000
0!
0"
0&
0'
#105000000
1!
1&
#110000000
0!
0&
#115000000
1!
1&
#120000000
0!
0&
#125000000
1!
1&
#130000000
0!
0&
#135000000
1!
1&
#140000000
0!
0&
#145000000
1!
1&
#150000000
0!
0&
#155000000
1!
1&
#160000000
0!
0&
#165000000
1!
1&
#170000000
0!
0&
#175000000
1!
1&
#180000000
0!
0&
#185000000
1!
1&
#190000000
0!
0&
#195000000
1!
1&
#200000000
0!
1#
1%
0&
#205000000
1!
1&
1*
#210000000
0!
0&
#215000000
1!
1&
b1 )
#220000000
0!
0#
0%
0&
#225000000
1!
1&
b10 )
#230000000
0!
1#
1%
0&
#235000000
1!
1&
b11 )
#240000000
0!
0#
0%
0&
#245000000
1!
1&
b100 )
#250000000
0!
0&
#255000000
1!
1&
b101 )
#260000000
0!
0&
#265000000
1!
1&
b110 )
#270000000
0!
0&
#275000000
1!
1&
b111 )
#280000000
0!
0&
#285000000
1!
1&
b1000 )
#290000000
0!
0&
#295000000
1!
1&
b1001 )
#300000000
0!
0&
#305000000
1!
1&
b1010 )
#310000000
0!
0&
#315000000
1!
1&
b1011 )
#320000000
0!
0&
#325000000
1!
1&
b1100 )
#330000000
0!
0&
#335000000
1!
1&
b1101 )
#340000000
0!
0&
#345000000
1!
1&
b1110 )
#350000000
0!
0&
#355000000
1!
1&
b1111 )
#360000000
0!
0&
#365000000
1!
1&
b0 )
0*
#370000000
0!
0&
#375000000
1!
1&
#380000000
0!
0&
#385000000
1!
1&
#390000000
0!
0&
#395000000
1!
1&
#400000000
0!
0&
#405000000
1!
1&
#410000000
0!
0&
#415000000
1!
1&
#420000000
0!
0&
#425000000
1!
1&
#430000000
0!
0&
#435000000
1!
1&
#440000000
0!
1#
1%
0&
#445000000
1!
1&
1*
#450000000
0!
0#
0%
0&
#455000000
1!
1&
b1 )
#460000000
0!
1#
1%
0&
#465000000
1!
1&
b10 )
#470000000
0!
0#
0%
0&
#475000000
1!
1&
b11 )
#480000000
0!
0&
#485000000
1!
1&
b100 )
#490000000
0!
1#
1%
0&
#495000000
1!
1&
b101 )
#500000000
0!
0&
#505000000
1!
1&
b110 )
#510000000
0!
0&
#515000000
1!
1&
b111 )
#520000000
0!
0&
#525000000
1!
1&
b1000 )
#530000000
0!
0&
#535000000
1!
1&
b1001 )
#540000000
0!
0&
#545000000
1!
1&
b1010 )
#550000000
0!
0&
#555000000
1!
1&
b1011 )
#560000000
0!
0&
#565000000
1!
1&
b1100 )
#570000000
0!
0&
#575000000
1!
1&
b1101 )
#580000000
0!
0&
#585000000
1!
1&
b1110 )
#590000000
0!
0&
#595000000
1!
1&
b1111 )
#600000000
0!
0&
#605000000
1!
1$
1&
1(
b0 )
0*
#610000000
0!
0&
#615000000
1!
0$
1&
0(
1*
#620000000
0!
0&
#625000000
1!
1&
b1 )
#630000000
0!
0&
#635000000
1!
1&
b10 )
#640000000
0!
0&
#645000000
1!
1&
b11 )
#650000000
0!
0&
#655000000
1!
1&
b100 )
#660000000
0!
0&
#665000000
1!
1&
b101 )
#670000000
0!
0&
#675000000
1!
1&
b110 )
#680000000
0!
0&
#685000000
1!
1&
b111 )
#690000000
0!
0#
0%
0&
#695000000
1!
1&
b1000 )
#700000000
0!
0&
#705000000
1!
1&
b1001 )
#710000000
0!
0&
#715000000
1!
1&
b1010 )
#720000000
0!
0&
#725000000
1!
1&
b1011 )
#730000000
0!
0&
#735000000
1!
1&
b1100 )
#740000000
0!
0&
#745000000
1!
1&
b1101 )
#750000000
0!
0&
#755000000
1!
1&
b1110 )
#760000000
0!
0&
#765000000
1!
1&
b1111 )
#770000000
0!
0&
#775000000
1!
1&
b0 )
0*
